prefixmaps/__init__.py
prefixmaps/data/__init__.py
prefixmaps/data/bioportal.csv
prefixmaps/data/bioportal.curated.yaml
prefixmaps/data/bioregistry.csv
prefixmaps/data/bioregistry.upper.csv
prefixmaps/data/contexts.curated.yaml
prefixmaps/data/go.csv
prefixmaps/data/linked_data.csv
prefixmaps/data/linked_data.curated.yaml
prefixmaps/data/merged.csv
prefixmaps/data/merged.monarch.csv
prefixmaps/data/merged.oak.csv
prefixmaps/data/obo.csv
prefixmaps/data/prefixcc.csv
prefixmaps/data/w3id.csv
prefixmaps/datamodel/__init__.py
prefixmaps/datamodel/context.py
prefixmaps/ingest/__init__.py
prefixmaps/ingest/etl_runner.py
prefixmaps/ingest/ingest_bioportal.py
prefixmaps/ingest/ingest_bioregistry.py
prefixmaps/ingest/ingest_go.py
prefixmaps/ingest/ingest_jsonld.py
prefixmaps/ingest/ingest_linkml.py
prefixmaps/ingest/ingest_shacl.py
prefixmaps/ingest/ingest_w3id.py
prefixmaps/io/__init__.py
prefixmaps/io/parser.py
prefixmaps/io/writer.py
prefixmaps-0.2.5.dist-info/LICENSE
prefixmaps-0.2.5.dist-info/METADATA
prefixmaps-0.2.5.dist-info/WHEEL
prefixmaps-0.2.5.dist-info/entry_points.txt
prefixmaps-0.2.5.dist-info/RECORD
