Metadata-Version: 2.1
Name: prefixmaps
Version: 0.2.5
Summary: A python library for retrieving semantic prefix maps
License: Apache-2.0
Keywords: semantic web,bioinformatics
Author: cmungall
Author-email: cjm@berkeleybop.org
Requires-Python: >=3.8,<4.0
Classifier: Development Status :: 1 - Planning
Classifier: License :: OSI Approved :: Apache Software License
Classifier: Programming Language :: Python :: 3
Classifier: Programming Language :: Python :: 3.8
Classifier: Programming Language :: Python :: 3.9
Classifier: Programming Language :: Python :: 3.10
Classifier: Programming Language :: Python :: 3.11
Classifier: Programming Language :: Python :: 3.12
Classifier: Topic :: Scientific/Engineering :: Bio-Informatics
Requires-Dist: curies (>=0.5.3)
Requires-Dist: pyyaml (>=5.3.1)
Project-URL: Bug Tracker, https://github.com/linkml/prefixmaps/issues
Project-URL: homepage, https://github.com/linkml/prefixmaps
Project-URL: repository, https://github.com/linkml/prefixmaps
